pyloc.py
test_pyloc.py
pyloc-0.2.0.dist-info/DESCRIPTION.rst
pyloc-0.2.0.dist-info/METADATA
pyloc-0.2.0.dist-info/RECORD
pyloc-0.2.0.dist-info/WHEEL
pyloc-0.2.0.dist-info/entry_points.txt
pyloc-0.2.0.dist-info/metadata.json
pyloc-0.2.0.dist-info/top_level.txt
